LICENCE
MANIFEST.in
README.rst
django_file_storage.py
setup.py
django_file_storage.egg-info/PKG-INFO
django_file_storage.egg-info/SOURCES.txt
django_file_storage.egg-info/dependency_links.txt
django_file_storage.egg-info/top_level.txt