Metadata-Version: 1.0
Name: django-file-storage
Version: 0.1.1
Summary: Set file storage as an environment variable in your Django application.
Home-page: http://github.com/meshy/django-file-storage
Author: Charlie Denton
Author-email: charlie@meshy.co.uk
License: LGPL
Platform: UNKNOWN
